nntemplate/__init__.py
nntemplate/experiment.py
nntemplate/hardware.py
nntemplate/training.py
nntemplate/callbacks/__init__.py
nntemplate/callbacks/log_artifacts.py
nntemplate/callbacks/optuna.py
nntemplate/config/__init__.py
nntemplate/config/cfg_dict.py
nntemplate/config/cfg_object.py
nntemplate/config/cfg_parser.py
nntemplate/data_augmentation/__init__.py
nntemplate/data_augmentation/data_augment.py
nntemplate/data_augmentation/random_dist.py
nntemplate/datasets/__init__.py
nntemplate/datasets/data_sources.py
nntemplate/datasets/dataset.py
nntemplate/datasets/hdf_py.py
nntemplate/datasets/path_utils.py
nntemplate/datasets/utils2d.py
nntemplate/hyperparameters_tuning/__init__.py
nntemplate/hyperparameters_tuning/generic_optimizer.py
nntemplate/hyperparameters_tuning/optuna.py
nntemplate/misc/__init__.py
nntemplate/misc/clip_pad.py
nntemplate/misc/function_tools.py
nntemplate/misc/lut.py
nntemplate/model/__init__.py
nntemplate/model/activation.py
nntemplate/model/common.py
nntemplate/model/smp.py
nntemplate/model/unet.py
nntemplate/model/wnet.py
nntemplate/task/__init__.py
nntemplate/task/optimizer.py
nntemplate/task/segmentation2D.py
nntemplate/task/task.py
nntemplate/task/test_time_augment.py
nntemplate/task/losses/__init__.py
nntemplate/task/losses/classification_losses.py
nntemplate/task/losses/loss_core.py
nntemplate/task/losses/segmentation_losses.py
nntemplate/task/lr_schedulers/__init__.py
nntemplate/task/lr_schedulers/schedulers_core.py
nntemplate/task/lr_schedulers/timm_schedulers.py
nntemplate/task/lr_schedulers/torch_schedulers.py
nntemplate/task/metrics/__init__.py
nntemplate/task/metrics/classification_metrics.py
nntemplate/task/metrics/metrics_core.py
nntemplate-0.0.5.dist-info/METADATA
nntemplate-0.0.5.dist-info/WHEEL
nntemplate-0.0.5.dist-info/top_level.txt
nntemplate-0.0.5.dist-info/RECORD
