Metadata-Version: 2.1
Name: nntemplate
Version: 0.0.5
Summary: Bundle of usefull tools for training segmentation or image classification neural networks.
Author-email: Gabriel Lepetit-Aimon <gabriel.lepetit-aimon@polymtl.ca>
Project-URL: Source, https://github.com/gabriel-lepetitaimon/nn-template
Requires-Python: >=3.10
Requires-Dist: albumentations
Requires-Dist: numpy
Requires-Dist: opencv-python-headless
Requires-Dist: optuna
Requires-Dist: parse
Requires-Dist: pandas
Requires-Dist: pytorch-lightning
Requires-Dist: pyyaml
Requires-Dist: segmentation-models-pytorch
Requires-Dist: torch
Requires-Dist: torchgeometry
Requires-Dist: torchmetrics
Requires-Dist: torchvision
Requires-Dist: ttach
Requires-Dist: webcolors
Requires-Dist: wandb
